maquinas/__init__.py
maquinas/exceptions.py
maquinas/io.py
maquinas/languages.py
maquinas/simulation.py
maquinas/simulation_grammar.py
maquinas/status.py
maquinas/utils.py
maquinas/contextfree/CFGParser.py
maquinas/contextfree/__init__.py
maquinas/contextfree/cfg.py
maquinas/contextfree/pda.py
maquinas/contextsensitive/__init__.py
maquinas/contextsensitive/alf.py
maquinas/parser/__init__.py
maquinas/parser/earley_parser.py
maquinas/recursivelyenumerable/__init__.py
maquinas/recursivelyenumerable/tm.py
maquinas/recursivelyenumerable/tspda.py
maquinas/regular/RE.py
maquinas/regular/REParser.py
maquinas/regular/RGParser.py
maquinas/regular/__init__.py
maquinas/regular/dfa.py
maquinas/regular/fa.py
maquinas/regular/minimization.py
maquinas/regular/ndfa.py
maquinas/regular/ndfa_e.py
maquinas/regular/reductions.py
maquinas/regular/rg.py
maquinas-0.3.2.0.dist-info/LICENSE
maquinas-0.3.2.0.dist-info/METADATA
maquinas-0.3.2.0.dist-info/WHEEL
maquinas-0.3.2.0.dist-info/entry_points.txt
maquinas-0.3.2.0.dist-info/top_level.txt
maquinas-0.3.2.0.dist-info/RECORD
